sudospawner/__init__.py
sudospawner/mediator.py
sudospawner/spawner.py
sudospawner/version.py
sudospawner-0.5.2.data/scripts/sudospawner
sudospawner-0.5.2.dist-info/METADATA
sudospawner-0.5.2.dist-info/RECORD
sudospawner-0.5.2.dist-info/WHEEL
sudospawner-0.5.2.dist-info/top_level.txt
